distutilazy/__init__.py
distutilazy/clean.py
distutilazy/pyinstaller.py
distutilazy/test.py
distutilazy/util.py
distutilazy/command/__init__.py
distutilazy/command/bdist_pyinstaller.py
distutilazy/command/clean_all.py
distutilazy/command/clean_jython_class.py
distutilazy/command/clean_pyc.py
distutilazy/command/test.py
distutilazy-0.5.1.data/scripts/distutilazy
distutilazy-0.5.1.dist-info/METADATA
distutilazy-0.5.1.dist-info/RECORD
distutilazy-0.5.1.dist-info/WHEEL
distutilazy-0.5.1.dist-info/top_level.txt
distutilazy-0.5.1.dist-info/zip-safe
